invenio_override/__init__.py
invenio_override/config.py
invenio_override/ext.py
invenio_override/search.py
invenio_override/views.py
invenio_override/webpack.py
invenio_override/assets/semantic-ui/js/invenio_override/theme.js
invenio_override/assets/semantic-ui/less/invenio_override/accounts.less
invenio_override/assets/semantic-ui/less/invenio_override/communities.less
invenio_override/assets/semantic-ui/less/invenio_override/footer.less
invenio_override/assets/semantic-ui/less/invenio_override/frontpage.less
invenio_override/assets/semantic-ui/less/invenio_override/header.less
invenio_override/assets/semantic-ui/less/invenio_override/login.less
invenio_override/assets/semantic-ui/less/invenio_override/macros.less
invenio_override/assets/semantic-ui/less/invenio_override/overrides.less
invenio_override/assets/semantic-ui/less/invenio_override/record.less
invenio_override/assets/semantic-ui/less/invenio_override/search.less
invenio_override/assets/semantic-ui/less/invenio_override/theme.less
invenio_override/assets/semantic-ui/less/invenio_override/variables.less
invenio_override/assets/semantic-ui/less/invenio_override/fonts/SourceSansPro/OFL.txt
invenio_override/assets/semantic-ui/less/invenio_override/fonts/SourceSansPro/SourceSansPro-Italic.ttf
invenio_override/assets/semantic-ui/less/invenio_override/fonts/SourceSansPro/SourceSansPro-Regular.ttf
invenio_override/static/kfu.ico
invenio_override/static/mug.ico
invenio_override/static/tug.ico
invenio_override/static/extra/orcid.png
invenio_override/static/images/KFU.svg
invenio_override/static/images/MUG.svg
invenio_override/static/images/TUG.png
invenio_override/static/images/TUGraz.png
invenio_override/static/images/diamond.svg
invenio_override/static/images/group-discussion.svg
invenio_override/static/images/icon_use.png
invenio_override/static/images/invenio-rdm.svg
invenio_override/static/images/invenioRDM.svg
invenio_override/static/images/inveniordm-tail.svg
invenio_override-0.0.6.dist-info/licenses/AUTHORS.rst
invenio_override-0.0.6.dist-info/licenses/LICENSE
invenio_override-0.0.6.dist-info/METADATA
invenio_override-0.0.6.dist-info/WHEEL
invenio_override-0.0.6.dist-info/entry_points.txt
invenio_override-0.0.6.dist-info/top_level.txt
invenio_override-0.0.6.dist-info/RECORD
