Metadata-Version: 2.4
Name: invenio-override
Version: 0.0.6
Summary: "Invenio module for sharedRDM theme."
Home-page: https://github.com/sharedRDM/invenio-override
Author: "sharedRDM"
Author-email: mojib.wali@tugraz.at
License: MIT
Keywords: invenio sharedRDM
Platform: any
Classifier: Environment :: Web Environment
Classifier: Intended Audience :: Developers
Classifier: License :: OSI Approved :: MIT License
Classifier: Operating System :: OS Independent
Classifier: Programming Language :: Python
Classifier: Topic :: Internet :: WWW/HTTP :: Dynamic Content
Classifier: Topic :: Software Development :: Libraries :: Python Modules
Classifier: Programming Language :: Python :: 3.12
Classifier: Programming Language :: Python :: 3.10
Classifier: Development Status :: 3 - Alpha
Requires-Python: >=3.12
License-File: LICENSE
License-File: AUTHORS.rst
Requires-Dist: opensearch-dsl<3.0.0,>=2.0.0
Requires-Dist: opensearch-py<3.0.0,>=2.0.0
Requires-Dist: invenio-global-search>=0.3.0
Requires-Dist: invenio-rdm-records>=18.0.0
Requires-Dist: invenio-app-rdm[opensearch2]<13.1.dev0,>=13.0.0b3.dev2
Provides-Extra: lom
Requires-Dist: invenio-global-search[lom]>=0.3.0; extra == "lom"
Provides-Extra: marc21
Requires-Dist: invenio-global-search[marc21]>=0.3.0; extra == "marc21"
Provides-Extra: tests
Requires-Dist: invenio-app<3.0.0,>=2.1.0; extra == "tests"
Requires-Dist: invenio-previewer>=2.2.0; extra == "tests"
Requires-Dist: pytest-black-ng>=0.4.0; extra == "tests"
Requires-Dist: invenio-global-search[lom,marc21]>=0.3.0; extra == "tests"
Requires-Dist: pytest-invenio<4.0.0,>=3.3.0; extra == "tests"
Requires-Dist: Sphinx>=4.5.0; extra == "tests"
Provides-Extra: opensearch2
Requires-Dist: invenio-search[opensearch2]<4.0.0,>=3.0.0; extra == "opensearch2"
Dynamic: license-file
